{
  "تسه1404": [
    {
      "t": "2025-05-10T22:48:36",
      "m": 1093929.0
    },
    {
      "t": "2025-05-10T22:57:34",
      "m": 1093362.0
    },
    {
      "t": "2025-05-10T23:07:49",
      "m": 1092795.0
    },
    {
      "t": "2025-05-10T23:16:55",
      "m": 1092660.0
    },
    {
      "t": "2025-05-10T23:25:39",
      "m": 1092525.0
    },
    {
      "t": "2025-05-10T23:45:53",
      "m": 1092462.0
    },
    {
      "t": "2025-05-11T00:02:07",
      "m": 1092399.0
    },
    {
      "t": "2025-05-11T00:13:40",
      "m": 1092352.0
    },
    {
      "t": "2025-05-11T00:22:31",
      "m": 1092305.0
    },
    {
      "t": "2025-05-11T08:52:18",
      "m": 1091056.0
    }
  ],
  "تسه1402": [
    {
      "t": "2025-05-10T22:48:36",
      "m": 1091375.0
    },
    {
      "t": "2025-05-10T22:57:34",
      "m": 1091086.5
    },
    {
      "t": "2025-05-10T23:07:49",
      "m": 1090798.0
    },
    {
      "t": "2025-05-10T23:16:55",
      "m": 1090628.0
    },
    {
      "t": "2025-05-10T23:25:39",
      "m": 1090458.0
    },
    {
      "t": "2025-05-10T23:45:53",
      "m": 1090222.0
    },
    {
      "t": "2025-05-11T00:02:07",
      "m": 1089986.0
    },
    {
      "t": "2025-05-11T00:13:40",
      "m": 1088951.0
    },
    {
      "t": "2025-05-11T00:22:31",
      "m": 1087916.0
    },
    {
      "t": "2025-05-11T08:52:18",
      "m": 1085775.0
    }
  ],
  "تسه1403": [
    {
      "t": "2025-05-10T22:48:36",
      "m": 1091583.0
    },
    {
      "t": "2025-05-10T22:57:34",
      "m": 1091174.0
    },
    {
      "t": "2025-05-10T23:07:49",
      "m": 1090765.0
    },
    {
      "t": "2025-05-10T23:16:55",
      "m": 1090533.5
    },
    {
      "t": "2025-05-10T23:25:39",
      "m": 1090302.0
    },
    {
      "t": "2025-05-10T23:45:53",
      "m": 1090150.0
    },
    {
      "t": "2025-05-11T00:02:07",
      "m": 1089998.0
    },
    {
      "t": "2025-05-11T00:13:40",
      "m": 1089773.5
    },
    {
      "t": "2025-05-11T00:22:31",
      "m": 1089549.0
    },
    {
      "t": "2025-05-11T08:52:18",
      "m": 1088377.0
    }
  ],
  "تملی1402": [
    {
      "t": "2025-05-10T22:29:51",
      "m": 718654.0
    },
    {
      "t": "2025-05-10T22:48:36",
      "m": 718654.0
    },
    {
      "t": "2025-05-10T22:57:34",
      "m": 718654.0
    },
    {
      "t": "2025-05-10T23:07:49",
      "m": 718654.0
    },
    {
      "t": "2025-05-10T23:16:55",
      "m": 718654.0
    },
    {
      "t": "2025-05-10T23:25:39",
      "m": 718654.0
    },
    {
      "t": "2025-05-10T23:45:53",
      "m": 718654.0
    },
    {
      "t": "2025-05-11T00:02:07",
      "m": 718654.0
    },
    {
      "t": "2025-05-11T00:13:40",
      "m": 718654.0
    },
    {
      "t": "2025-05-11T00:22:31",
      "m": 718654.0
    }
  ],
  "تملی1403": [
    {
      "t": "2025-05-10T22:29:51",
      "m": 718654.0
    },
    {
      "t": "2025-05-10T22:48:36",
      "m": 718654.0
    },
    {
      "t": "2025-05-10T22:57:34",
      "m": 718654.0
    },
    {
      "t": "2025-05-10T23:07:49",
      "m": 718654.0
    },
    {
      "t": "2025-05-10T23:16:55",
      "m": 718654.0
    },
    {
      "t": "2025-05-10T23:25:39",
      "m": 718654.0
    },
    {
      "t": "2025-05-10T23:45:53",
      "m": 718654.0
    },
    {
      "t": "2025-05-11T00:02:07",
      "m": 718654.0
    },
    {
      "t": "2025-05-11T00:13:40",
      "m": 718654.0
    },
    {
      "t": "2025-05-11T00:22:31",
      "m": 718654.0
    }
  ]
}