[
    {
        "time": "09:30:07",
        "l18": "تسه۱۴۰۴",
        "l30": "امتیاز تسهیلات مسکن سال۱۴۰۴",
        "isin": "IRO6MSKZ4041",
        "id": 17805801742135377,
        "cs": "اوراق حق تقدم استفاده از تسهیلات مسکن",
        "cs_id": 59,
        "z": 4427343,
        "bvol": 1,
        "mv": 6175877844420,
        "eps": null,
        "pe": null,
        "tmin": 1314326,
        "tmax": 1452676,
        "pmin": 1371100,
        "pmax": 1405000,
        "py": 1383501,
        "pf": 1371100,
        "pl": 1395000,
        "plc": 11499,
        "plp": 0.83,
        "pc": 1394940,
        "pcc": 11439,
        "pcp": 0.83,
        "tno": 902,
        "tvol": 71897,
        "tval": 100292029902,
        "Buy_CountI": 74,
        "Buy_CountN": 0,
        "Sell_CountI": 774,
        "Sell_CountN": 0,
        "Buy_I_Volume": 71141,
        "Buy_N_Volume": 0,
        "Sell_I_Volume": 71141,
        "Sell_N_Volume": 0,
        "zd1": 1,
        "qd1": 1058,
        "pd1": 1394000,
        "po1": 1395000,
        "qo1": 164,
        "zo1": 4,
        "zd2": 1,
        "qd2": 880,
        "pd2": 1393002,
        "po2": 1398000,
        "qo2": 14,
        "zo2": 2,
        "zd3": 1,
        "qd3": 737,
        "pd3": 1393001,
        "po3": 1398999,
        "qo3": 17,
        "zo3": 1,
        "zd4": 2,
        "qd4": 23,
        "pd4": 1393000,
        "po4": 1399000,
        "qo4": 922,
        "zo4": 9,
        "zd5": 1,
        "qd5": 543,
        "pd5": 1391300,
        "po5": 1399980,
        "qo5": 1295,
        "zo5": 2
    },
    {
        "time": "09:30:04",
        "l18": "تسه۱۴۰۳",
        "l30": "امتیاز تسهیلات مسکن سال۱۴۰۳",
        "isin": "IRO6MSKZ4031",
        "id": 67245068099249026,
        "cs": "اوراق حق تقدم استفاده از تسهیلات مسکن",
        "cs_id": 59,
        "z": 4427343,
        "bvol": 1,
        "mv": 6146878747770,
        "eps": null,
        "pe": null,
        "tmin": 1307863,
        "tmax": 1445531,
        "pmin": 1340001,
        "pmax": 1400001,
        "py": 1376697,
        "pf": 1350000,
        "pl": 1391005,
        "plc": 14308,
        "plp": 1.04,
        "pc": 1388390,
        "pcc": 11693,
        "pcp": 0.85,
        "tno": 106,
        "tvol": 10590,
        "tval": 14703051406,
        "Buy_CountI": 19,
        "Buy_CountN": 0,
        "Sell_CountI": 93,
        "Sell_CountN": 0,
        "Buy_I_Volume": 10292,
        "Buy_N_Volume": 0,
        "Sell_I_Volume": 10292,
        "Sell_N_Volume": 0,
        "zd1": 1,
        "qd1": 1480,
        "pd1": 1392000,
        "po1": 1399000,
        "qo1": 1566,
        "zo1": 2,
        "zd2": 1,
        "qd2": 662,
        "pd2": 1391005,
        "po2": 1399998,
        "qo2": 41,
        "zo2": 1,
        "zd3": 2,
        "qd3": 582,
        "pd3": 1391004,
        "po3": 1399999,
        "qo3": 6,
        "zo3": 3,
        "zd4": 1,
        "qd4": 375,
        "pd4": 1391000,
        "po4": 1400000,
        "qo4": 505,
        "zo4": 5,
        "zd5": 5,
        "qd5": 4248,
        "pd5": 1390000,
        "po5": 1400001,
        "qo5": 325,
        "zo5": 3
    },
    {
        "time": "09:29:17",
        "l18": "تسه۱۴۰۲",
        "l30": "امتیازتسهیلات مسکن سال۱۴۰۲",
        "isin": "IRO6MSKZ4111",
        "id": 28725056634066391,
        "cs": "اوراق حق تقدم استفاده از تسهیلات مسکن",
        "cs_id": 59,
        "z": 4427343,
        "bvol": 1,
        "mv": 6131073133260,
        "eps": null,
        "pe": null,
        "tmin": 1310829,
        "tmax": 1448811,
        "pmin": 1370000,
        "pmax": 1400000,
        "py": 1379820,
        "pf": 1370000,
        "pl": 1400000,
        "plc": 20180,
        "plp": 1.46,
        "pc": 1384820,
        "pcc": 5000,
        "pcp": 0.36,
        "tno": 42,
        "tvol": 2285,
        "tval": 3164313898,
        "Buy_CountI": 10,
        "Buy_CountN": 0,
        "Sell_CountI": 39,
        "Sell_CountN": 0,
        "Buy_I_Volume": 2285,
        "Buy_N_Volume": 0,
        "Sell_I_Volume": 2285,
        "Sell_N_Volume": 0,
        "zd1": 1,
        "qd1": 1049,
        "pd1": 1390013,
        "po1": 1400000,
        "qo1": 38,
        "zo1": 2,
        "zd2": 1,
        "qd2": 798,
        "pd2": 1390009,
        "po2": 1419997,
        "qo2": 216,
        "zo2": 1,
        "zd3": 2,
        "qd3": 2109,
        "pd3": 1390000,
        "po3": 1419998,
        "qo3": 17,
        "zo3": 2,
        "zd4": 1,
        "qd4": 265,
        "pd4": 1370010,
        "po4": 1419999,
        "qo4": 10,
        "zo4": 1,
        "zd5": 1,
        "qd5": 200,
        "pd5": 1370000,
        "po5": 1420000,
        "qo5": 94,
        "zo5": 4
    },
    {
        "time": "09:22:52",
        "l18": "تملی۱۴۰۳",
        "l30": "امتیازتسهیلات ملی سال ۱۴۰۳",
        "isin": "IRO6MELZ4031",
        "id": 22988982483538160,
        "cs": "اوراق حق تقدم استفاده از تسهیلات مسکن",
        "cs_id": 59,
        "z": 512339,
        "bvol": 1,
        "mv": 533275733235,
        "eps": null,
        "pe": null,
        "tmin": 941735,
        "tmax": 1040865,
        "pmin": 1040865,
        "pmax": 1040865,
        "py": 991300,
        "pf": 1040865,
        "pl": 1040865,
        "plc": 49565,
        "plp": 5,
        "pc": 1040865,
        "pcc": 49565,
        "pcp": 5,
        "tno": 5,
        "tvol": 381,
        "tval": 396569565,
        "Buy_CountI": 3,
        "Buy_CountN": 0,
        "Sell_CountI": 3,
        "Sell_CountN": 0,
        "Buy_I_Volume": 381,
        "Buy_N_Volume": 0,
        "Sell_I_Volume": 381,
        "Sell_N_Volume": 0,
        "zd1": 0,
        "qd1": 0,
        "pd1": 0,
        "po1": 1040865,
        "qo1": 148,
        "zo1": 2,
        "zd2": 0,
        "qd2": 0,
        "pd2": 0,
        "po2": 0,
        "qo2": 0,
        "zo2": 0,
        "zd3": 0,
        "qd3": 0,
        "pd3": 0,
        "po3": 0,
        "qo3": 0,
        "zo3": 0,
        "zd4": 0,
        "qd4": 0,
        "pd4": 0,
        "po4": 0,
        "qo4": 0,
        "zo4": 0,
        "zd5": 0,
        "qd5": 0,
        "pd5": 0,
        "po5": 0,
        "qo5": 0,
        "zo5": 0
    },
    {
        "time": "09:14:38",
        "l18": "تملی۱۴۰۲",
        "l30": "امتیازتسهیلات ملی سال ۱۴۰۲",
        "isin": "IRO6MELZ4021",
        "id": 51360499382537160,
        "cs": "اوراق حق تقدم استفاده از تسهیلات مسکن",
        "cs_id": 59,
        "z": 512339,
        "bvol": 1,
        "mv": 509777305000,
        "eps": null,
        "pe": null,
        "tmin": 949999,
        "tmax": 1049997,
        "pmin": 995000,
        "pmax": 995000,
        "py": 999998,
        "pf": 995000,
        "pl": 995000,
        "plc": -4998,
        "plp": -0.5,
        "pc": 995000,
        "pcc": -4998,
        "pcp": -0.5,
        "tno": 1,
        "tvol": 280,
        "tval": 278600000,
        "Buy_CountI": 1,
        "Buy_CountN": 0,
        "Sell_CountI": 1,
        "Sell_CountN": 0,
        "Buy_I_Volume": 280,
        "Buy_N_Volume": 0,
        "Sell_I_Volume": 280,
        "Sell_N_Volume": 0,
        "zd1": 1,
        "qd1": 84,
        "pd1": 949999,
        "po1": 0,
        "qo1": 0,
        "zo1": 0,
        "zd2": 0,
        "qd2": 0,
        "pd2": 0,
        "po2": 0,
        "qo2": 0,
        "zo2": 0,
        "zd3": 0,
        "qd3": 0,
        "pd3": 0,
        "po3": 0,
        "qo3": 0,
        "zo3": 0,
        "zd4": 0,
        "qd4": 0,
        "pd4": 0,
        "po4": 0,
        "qo4": 0,
        "zo4": 0,
        "zd5": 0,
        "qd5": 0,
        "pd5": 0,
        "po5": 0,
        "qo5": 0,
        "zo5": 0
    }
]