{
    "metal_precious": [
        {
            "date": "1404/07/01",
            "time": "04:46",
            "time_unix": 1758590168,
            "symbol": "XAUUSD",
            "name": "انس طلا",
            "price": 3755.25,
            "change_value": 7.67,
            "change_percent": 0.2,
            "unit": "دلار"
        },
        {
            "date": "1404/07/01",
            "time": "04:46",
            "time_unix": 1758590168,
            "symbol": "XAGUSD",
            "name": "انس نقره",
            "price": 43.97,
            "change_value": -0.08,
            "change_percent": -0.18,
            "unit": "دلار"
        },
        {
            "date": "1404/07/01",
            "time": "04:46",
            "time_unix": 1758590168,
            "symbol": "XPTUSD",
            "name": "انس پلاتین",
            "price": 1429.6,
            "change_value": 2.55,
            "change_percent": 0.18,
            "unit": "دلار"
        },
        {
            "date": "1404/07/01",
            "time": "04:46",
            "time_unix": 1758590168,
            "symbol": "XPDUSD",
            "name": "انس پالادیوم",
            "price": 1222.5,
            "change_value": 4.25,
            "change_percent": 0.35,
            "unit": "دلار"
        }
    ],
    "metal_base": [
        {
            "date": "1404/07/01",
            "time": "04:46",
            "time_unix": 1758590168,
            "symbol": "Cu",
            "name": "مس",
            "price": 10015.8,
            "change_value": 14.8,
            "change_percent": 0.15,
            "unit": "دلار"
        },
        {
            "date": "1404/07/01",
            "time": "04:46",
            "time_unix": 1758590219,
            "symbol": "Al",
            "name": "آلومینیوم",
            "price": 2648.1,
            "change_value": 5,
            "change_percent": 0.19,
            "unit": "دلار"
        },
        {
            "date": "1404/07/01",
            "time": "04:46",
            "time_unix": 1758590168,
            "symbol": "Zn",
            "name": "روی",
            "price": 2903.6,
            "change_value": 1.95,
            "change_percent": 0.07,
            "unit": "دلار"
        },
        {
            "date": "1404/07/01",
            "time": "04:45",
            "time_unix": 1758590119,
            "symbol": "Pb",
            "name": "سرب",
            "price": 1999.45,
            "change_value": -2.53,
            "change_percent": -0.13,
            "unit": "دلار"
        },
        {
            "date": "1404/07/01",
            "time": "04:46",
            "time_unix": 1758590161,
            "symbol": "Sn",
            "name": "قلع",
            "price": 33952,
            "change_value": -175.59,
            "change_percent": -0.51,
            "unit": "دلار"
        },
        {
            "date": "1404/07/01",
            "time": "04:46",
            "time_unix": 1758590168,
            "symbol": "Ni",
            "name": "نیکل",
            "price": 15216.5,
            "change_value": 19.37,
            "change_percent": 0.13,
            "unit": "دلار"
        }
    ],
    "energy": [
        {
            "date": "1404/07/01",
            "time": "04:45",
            "time_unix": 1758590119,
            "symbol": "BRENT",
            "name": "نفت برنت",
            "price": 66.57,
            "change_value": -0.04,
            "change_percent": -0.06,
            "unit": "دلار"
        },
        {
            "date": "1404/07/01",
            "time": "04:45",
            "time_unix": 1758590119,
            "symbol": "WTI",
            "name": "نفت سبک",
            "price": 62.33,
            "change_value": -0.02,
            "change_percent": -0.03,
            "unit": "دلار"
        },
        {
            "date": "1404/07/01",
            "time": "04:45",
            "time_unix": 1758590119,
            "symbol": "GAS",
            "name": "گاز طبیعی",
            "price": 3.089,
            "change_value": -0.008,
            "change_percent": -0.26,
            "unit": "دلار"
        },
        {
            "date": "1404/07/01",
            "time": "04:45",
            "time_unix": 1758590119,
            "symbol": "RBOB",
            "name": "بنزین",
            "price": 1.9792,
            "change_value": -0.0008,
            "change_percent": -0.04,
            "unit": "دلار"
        },
        {
            "date": "1404/07/01",
            "time": "04:45",
            "time_unix": 1758590119,
            "symbol": "GASOIL",
            "name": "گازوییل",
            "price": 689.75,
            "change_value": -0.13,
            "change_percent": -0.02,
            "unit": "دلار"
        }
    ]
}