{"currency":[{"date":"1404/03/19","time":"11:16","time_unix":1749455160,"symbol":"USD","name_en":"US Dollar","name":"دلار","price":82350,"change_value":0,"change_percent":0,"unit":"تومان"},{"date":"1404/03/19","time":"11:17","time_unix":1749455220,"symbol":"EUR","name_en":"Euro","name":"یورو","price":94080,"change_value":301,"change_percent":0.32,"unit":"تومان"},{"date":"1404/03/19","time":"11:17","time_unix":1749455220,"symbol":"AED","name_en":"UAE Dirham","name":"درهم امارات","price":22523,"change_value":17,"change_percent":0.08,"unit":"تومان"},{"date":"1404/03/19","time":"11:18","time_unix":1749455280,"symbol":"GBP","name_en":"British Pound","name":"پوند","price":111730,"change_value":470,"change_percent":0.42,"unit":"تومان"},{"date":"1404/03/19","time":"11:17","time_unix":1749455220,"symbol":"JPY","name_en":"Japanese Yen","name":"یکصد ین ژاپن","price":57317,"change_value":292,"change_percent":0.51,"unit":"تومان"},{"date":"1404/03/19","time":"11:17","time_unix":1749455220,"symbol":"KWD","name_en":"Kuwaiti Dinar","name":"دینار کویت","price":269120,"change_value":-260,"change_percent":-0.1,"unit":"تومان"},{"date":"1404/03/19","time":"11:18","time_unix":1749455280,"symbol":"AUD","name_en":"Australian Dollar","name":"دلار استرالیا","price":53670,"change_value":250,"change_percent":0.47,"unit":"تومان"},{"date":"1404/03/19","time":"11:17","time_unix":1749455220,"symbol":"CAD","name_en":"Canadian Dollar","name":"دلار کانادا","price":60190,"change_value":90,"change_percent":0.15,"unit":"تومان"},{"date":"1404/03/19","time":"11:18","time_unix":1749455280,"symbol":"CNY","name_en":"Chinese Yuan","name":"یوآن چین","price":11470,"change_value":20,"change_percent":0.17,"unit":"تومان"},{"date":"1404/03/18","time":"18:28","time_unix":1749394680,"symbol":"TRY","name_en":"Turkish Lira","name":"لیر ترکیه","price":2100,"change_value":10,"change_percent":0.48,"unit":"تومان"},{"date":"1404/03/19","time":"11:17","time_unix":1749455220,"symbol":"SAR","name_en":"Saudi Riyal","name":"ریال عربستان","price":22008,"change_value":37,"change_percent":0.17,"unit":"تومان"},{"date":"1404/03/19","time":"11:17","time_unix":1749455220,"symbol":"CHF","name_en":"Swiss Franc","name":"فرانک سوئیس","price":100430,"change_value":440,"change_percent":0.44,"unit":"تومان"},{"date":"1404/03/19","time":"11:03","time_unix":1749454380,"symbol":"INR","name_en":"Indian Rupee","name":"روپیه هند","price":964,"change_value":3,"change_percent":0.31,"unit":"تومان"},{"date":"1404/03/19","time":"11:18","time_unix":1749455280,"symbol":"PKR","name_en":"Pakistani Rupee","name":"روپیه پاکستان","price":293,"change_value":1,"change_percent":0.41,"unit":"تومان"},{"date":"1404/03/19","time":"11:03","time_unix":1749454380,"symbol":"IQD","name_en":"Iraqi Dinar","name":"دینار عراق","price":57,"change_value":1,"change_percent":1.97,"unit":"تومان"},{"date":"1404/03/18","time":"11:31","time_unix":1749369660,"symbol":"SYP","name_en":"Syrian Lira","name":"لیر سوریه","price":6,"change_value":0,"change_percent":0,"unit":"تومان"},{"date":"1404/03/19","time":"11:12","time_unix":1749454920,"symbol":"SEK","name_en":"Swedish Krona","name":"کرون سوئد","price":8580,"change_value":40,"change_percent":0.47,"unit":"تومان"},{"date":"1404/03/19","time":"11:18","time_unix":1749455280,"symbol":"QAR","name_en":"Qatari Riyal","name":"ریال قطر","price":23390,"change_value":770,"change_percent":3.4,"unit":"تومان"},{"date":"1404/03/19","time":"11:18","time_unix":1749455280,"symbol":"OMR","name_en":"Omani Rial","name":"ریال عمان","price":213920,"change_value":110,"change_percent":0.05,"unit":"تومان"},{"date":"1404/03/19","time":"11:18","time_unix":1749455280,"symbol":"BHD","name_en":"Bahraini Dinar","name":"دینار بحرین","price":218410,"change_value":50,"change_percent":0.02,"unit":"تومان"},{"date":"1404/03/19","time":"11:18","time_unix":1749455280,"symbol":"AFN","name_en":"Afghan Afghani","name":"افغانی","price":1197,"change_value":-25,"change_percent":-2.09,"unit":"تومان"},{"date":"1404/03/19","time":"11:18","time_unix":1749455280,"symbol":"MYR","name_en":"Malaysian Ringgit","name":"رینگیت مالزی","price":19460,"change_value":-20,"change_percent":-0.1,"unit":"تومان"},{"date":"1404/03/19","time":"11:18","time_unix":1749455280,"symbol":"THB","name_en":"Thai Baht","name":"بات تایلند","price":2522,"change_value":10,"change_percent":0.4,"unit":"تومان"},{"date":"1404/03/19","time":"11:18","time_unix":1749455280,"symbol":"RUB","name_en":"Russian Ruble","name":"روبل روسیه","price":1049,"change_value":-5,"change_percent":-0.48,"unit":"تومان"},{"date":"1404/03/19","time":"11:18","time_unix":1749455280,"symbol":"AZN","name_en":"Azerbaijani Manat","name":"منات آذربایجان","price":48600,"change_value":50,"change_percent":0.1,"unit":"تومان"},{"date":"1404/03/19","time":"11:18","time_unix":1749455280,"symbol":"AMD","name_en":"Armenian Dram","name":"درام ارمنستان","price":231,"change_value":16,"change_percent":7.44,"unit":"تومان"},{"date":"1404/03/19","time":"11:18","time_unix":1749455280,"symbol":"GEL","name_en":"Georgian Lari","name":"لاری گرجستان","price":30290,"change_value":10,"change_percent":0.03,"unit":"تومان"}]}