{
    "currency": [
        {
            "date": "1404/07/15",
            "time": "18:25",
            "time_unix": 1759848950,
            "symbol": "USD",
            "name_en": "US Dollar",
            "name": "دلار",
            "price": 113870,
            "change_value": 2710,
            "change_percent": 2.44,
            "unit": "تومان"
        },
        {
            "date": "1404/07/15",
            "time": "18:25",
            "time_unix": 1759848949,
            "symbol": "EUR",
            "name_en": "Euro",
            "name": "یورو",
            "price": 132770,
            "change_value": 2620,
            "change_percent": 2.01,
            "unit": "تومان"
        },
        {
            "date": "1404/07/15",
            "time": "18:25",
            "time_unix": 1759848949,
            "symbol": "AED",
            "name_en": "UAE Dirham",
            "name": "درهم امارات",
            "price": 31017,
            "change_value": 734,
            "change_percent": 2.42,
            "unit": "تومان"
        },
        {
            "date": "1404/07/15",
            "time": "18:25",
            "time_unix": 1759848944,
            "symbol": "GBP",
            "name_en": "British Pound",
            "name": "پوند",
            "price": 152900,
            "change_value": 3160,
            "change_percent": 2.11,
            "unit": "تومان"
        },
        {
            "date": "1404/07/15",
            "time": "18:25",
            "time_unix": 1759848949,
            "symbol": "JPY",
            "name_en": "Japanese Yen",
            "name": "یکصد ین ژاپن",
            "price": 75343,
            "change_value": 1272,
            "change_percent": 1.72,
            "unit": "تومان"
        },
        {
            "date": "1404/07/15",
            "time": "18:25",
            "time_unix": 1759848949,
            "symbol": "KWD",
            "name_en": "Kuwaiti Dinar",
            "name": "دینار کویت",
            "price": 372400,
            "change_value": 8570,
            "change_percent": 2.36,
            "unit": "تومان"
        },
        {
            "date": "1404/07/15",
            "time": "18:25",
            "time_unix": 1759848949,
            "symbol": "AUD",
            "name_en": "Australian Dollar",
            "name": "دلار استرالیا",
            "price": 75020,
            "change_value": 1490,
            "change_percent": 2.03,
            "unit": "تومان"
        },
        {
            "date": "1404/07/15",
            "time": "18:25",
            "time_unix": 1759848940,
            "symbol": "CAD",
            "name_en": "Canadian Dollar",
            "name": "دلار کانادا",
            "price": 81620,
            "change_value": 1920,
            "change_percent": 2.41,
            "unit": "تومان"
        },
        {
            "date": "1404/07/15",
            "time": "18:17",
            "time_unix": 1759848431,
            "symbol": "CNY",
            "name_en": "Chinese Yuan",
            "name": "یوآن چین",
            "price": 16000,
            "change_value": 380,
            "change_percent": 2.43,
            "unit": "تومان"
        },
        {
            "date": "1404/07/15",
            "time": "15:57",
            "time_unix": 1759840035,
            "symbol": "TRY",
            "name_en": "Turkish Lira",
            "name": "لیر ترکیه",
            "price": 2730,
            "change_value": 60,
            "change_percent": 2.25,
            "unit": "تومان"
        },
        {
            "date": "1404/07/15",
            "time": "18:25",
            "time_unix": 1759848950,
            "symbol": "SAR",
            "name_en": "Saudi Riyal",
            "name": "ریال عربستان",
            "price": 30394,
            "change_value": 716,
            "change_percent": 2.41,
            "unit": "تومان"
        },
        {
            "date": "1404/07/15",
            "time": "18:25",
            "time_unix": 1759848949,
            "symbol": "CHF",
            "name_en": "Swiss Franc",
            "name": "فرانک سوئیس",
            "price": 142670,
            "change_value": 2950,
            "change_percent": 2.11,
            "unit": "تومان"
        },
        {
            "date": "1404/07/15",
            "time": "18:25",
            "time_unix": 1759848936,
            "symbol": "INR",
            "name_en": "Indian Rupee",
            "name": "روپیه هند",
            "price": 1284,
            "change_value": 30,
            "change_percent": 2.39,
            "unit": "تومان"
        },
        {
            "date": "1404/07/15",
            "time": "18:25",
            "time_unix": 1759848940,
            "symbol": "PKR",
            "name_en": "Pakistani Rupee",
            "name": "روپیه پاکستان",
            "price": 403,
            "change_value": 9,
            "change_percent": 2.33,
            "unit": "تومان"
        },
        {
            "date": "1404/07/15",
            "time": "18:17",
            "time_unix": 1759848431,
            "symbol": "IQD",
            "name_en": "Iraqi Dinar",
            "name": "دینار عراق",
            "price": 87,
            "change_value": 0,
            "change_percent": 0.58,
            "unit": "تومان"
        },
        {
            "date": "1404/07/15",
            "time": "15:48",
            "time_unix": 1759839528,
            "symbol": "SYP",
            "name_en": "Syrian Lira",
            "name": "لیر سوریه",
            "price": 8,
            "change_value": 0,
            "change_percent": 2.35,
            "unit": "تومان"
        },
        {
            "date": "1404/07/15",
            "time": "18:25",
            "time_unix": 1759848906,
            "symbol": "SEK",
            "name_en": "Swedish Krona",
            "name": "کرون سوئد",
            "price": 12110,
            "change_value": 260,
            "change_percent": 2.19,
            "unit": "تومان"
        },
        {
            "date": "1404/07/15",
            "time": "18:25",
            "time_unix": 1759848940,
            "symbol": "QAR",
            "name_en": "Qatari Riyal",
            "name": "ریال قطر",
            "price": 32270,
            "change_value": 640,
            "change_percent": 2.02,
            "unit": "تومان"
        },
        {
            "date": "1404/07/15",
            "time": "18:25",
            "time_unix": 1759848949,
            "symbol": "OMR",
            "name_en": "Omani Rial",
            "name": "ریال عمان",
            "price": 295790,
            "change_value": 6920,
            "change_percent": 2.4,
            "unit": "تومان"
        },
        {
            "date": "1404/07/15",
            "time": "18:25",
            "time_unix": 1759848950,
            "symbol": "BHD",
            "name_en": "Bahraini Dinar",
            "name": "دینار بحرین",
            "price": 302070,
            "change_value": 7070,
            "change_percent": 2.4,
            "unit": "تومان"
        },
        {
            "date": "1404/07/15",
            "time": "18:25",
            "time_unix": 1759848940,
            "symbol": "AFN",
            "name_en": "Afghan Afghani",
            "name": "افغانی",
            "price": 1711,
            "change_value": 47,
            "change_percent": 2.82,
            "unit": "تومان"
        },
        {
            "date": "1404/07/15",
            "time": "18:25",
            "time_unix": 1759848936,
            "symbol": "MYR",
            "name_en": "Malaysian Ringgit",
            "name": "رینگیت مالزی",
            "price": 27040,
            "change_value": 650,
            "change_percent": 2.46,
            "unit": "تومان"
        },
        {
            "date": "1404/07/15",
            "time": "18:25",
            "time_unix": 1759848936,
            "symbol": "THB",
            "name_en": "Thai Baht",
            "name": "بات تایلند",
            "price": 3508,
            "change_value": 83,
            "change_percent": 2.42,
            "unit": "تومان"
        },
        {
            "date": "1404/07/15",
            "time": "18:25",
            "time_unix": 1759848940,
            "symbol": "RUB",
            "name_en": "Russian Ruble",
            "name": "روبل روسیه",
            "price": 1414,
            "change_value": 62,
            "change_percent": 4.59,
            "unit": "تومان"
        },
        {
            "date": "1404/07/15",
            "time": "18:25",
            "time_unix": 1759848940,
            "symbol": "AZN",
            "name_en": "Azerbaijani Manat",
            "name": "منات آذربایجان",
            "price": 67190,
            "change_value": 1590,
            "change_percent": 2.42,
            "unit": "تومان"
        },
        {
            "date": "1404/07/15",
            "time": "18:21",
            "time_unix": 1759848719,
            "symbol": "AMD",
            "name_en": "Armenian Dram",
            "name": "درام ارمنستان",
            "price": 298,
            "change_value": 7,
            "change_percent": 2.41,
            "unit": "تومان"
        },
        {
            "date": "1404/07/15",
            "time": "18:25",
            "time_unix": 1759848940,
            "symbol": "GEL",
            "name_en": "Georgian Lari",
            "name": "لاری گرجستان",
            "price": 41960,
            "change_value": 1050,
            "change_percent": 2.57,
            "unit": "تومان"
        }
    ]
}