[
  {
    "symbol": "XAUUSD",
    "median": 3306.25,
    "period_end": "2025-04-30T11:48:58.330004+00:00"
  },
  {
    "symbol": "XAGUSD",
    "median": 32.79,
    "period_end": "2025-04-30T11:48:58.330004+00:00"
  },
  {
    "symbol": "XPTUSD",
    "median": 977.55,
    "period_end": "2025-04-30T11:48:58.330004+00:00"
  },
  {
    "symbol": "XPDUSD",
    "median": 930.0,
    "period_end": "2025-04-30T11:48:58.330004+00:00"
  },
  {
    "symbol": "Cu",
    "median": 9331.75,
    "period_end": "2025-04-30T11:48:58.330004+00:00"
  },
  {
    "symbol": "Al",
    "median": 2455.0,
    "period_end": "2025-04-30T11:48:58.330004+00:00"
  },
  {
    "symbol": "Zn",
    "median": 2640.65,
    "period_end": "2025-04-30T11:48:58.330004+00:00"
  },
  {
    "symbol": "Pb",
    "median": 1977.08,
    "period_end": "2025-04-30T11:48:58.330004+00:00"
  },
  {
    "symbol": "Sn",
    "median": 31795.0,
    "period_end": "2025-04-30T11:48:58.330004+00:00"
  },
  {
    "symbol": "Ni",
    "median": 15584.5,
    "period_end": "2025-04-30T11:48:58.330004+00:00"
  },
  {
    "symbol": "BRENT",
    "median": 62.63,
    "period_end": "2025-04-30T11:48:58.330004+00:00"
  },
  {
    "symbol": "OPEC",
    "median": 68.16,
    "period_end": "2025-04-30T11:48:58.330004+00:00"
  },
  {
    "symbol": "WTI",
    "median": 59.71,
    "period_end": "2025-04-30T11:48:58.330004+00:00"
  },
  {
    "symbol": "GAS",
    "median": 3.372,
    "period_end": "2025-04-30T11:48:58.330004+00:00"
  },
  {
    "symbol": "RBOB",
    "median": 2.0367,
    "period_end": "2025-04-30T11:48:58.330004+00:00"
  },
  {
    "symbol": "GASOIL",
    "median": 604.63,
    "period_end": "2025-04-30T11:48:58.330004+00:00"
  }
]